spotify_login/__init__.py
spotify_login/package.py
spotify_login-1.0.dist-info/METADATA
spotify_login-1.0.dist-info/WHEEL
spotify_login-1.0.dist-info/top_level.txt
spotify_login-1.0.dist-info/RECORD
